poetry_install_prod_plugin/__init__.py
poetry_install_prod_plugin/plugin.py
poetry_install_prod_plugin/py.typed
poetry_install_prod_plugin-0.1.2.dist-info/LICENSE.txt
poetry_install_prod_plugin-0.1.2.dist-info/METADATA
poetry_install_prod_plugin-0.1.2.dist-info/WHEEL
poetry_install_prod_plugin-0.1.2.dist-info/entry_points.txt
poetry_install_prod_plugin-0.1.2.dist-info/RECORD
